<?xml version="1.0" encoding="utf-8"?>
<AdditionalInfo>
  <CTypeInfo>
      <RtlPort>
        <name>begin_r</name>
        <type>Unsigned</type>
        <fractionWidth>0</fractionWidth>
      </RtlPort>
      <RtlPort>
        <name>data_in</name>
        <type>Unsigned</type>
        <fractionWidth>0</fractionWidth>
      </RtlPort>
      <RtlPort>
        <name>data_out</name>
        <type>Unsigned</type>
        <fractionWidth>0</fractionWidth>
      </RtlPort>
      <RtlPort>
        <name>end_r</name>
        <type>Unsigned</type>
        <fractionWidth>0</fractionWidth>
      </RtlPort>
      <RtlPort>
        <name>start_r</name>
        <type>Unsigned</type>
        <fractionWidth>0</fractionWidth>
      </RtlPort>
  </CTypeInfo>
  <DesignConstraint>
    <clk_period>10</clk_period>
  </DesignConstraint>
  <Machine>64</Machine>
  <modelParameters>
    <combinational>0</combinational>
    <latency>0</latency>
    <II>x</II>
  </modelParameters>
</AdditionalInfo>
